simple_mailer/captcha.py
simple_mailer/checks.py
simple_mailer/config.py
simple_mailer/dispatcher.py
simple_mailer/exceptions.py
simple_mailer/http.py
simple_mailer/mailer.py
simple_mailer/utils.py
simple_mailer/web.py
simple_mailer-1.1.1.dist-info/LICENSE
simple_mailer-1.1.1.dist-info/METADATA
simple_mailer-1.1.1.dist-info/WHEEL
simple_mailer-1.1.1.dist-info/entry_points.txt
simple_mailer-1.1.1.dist-info/top_level.txt
simple_mailer-1.1.1.dist-info/RECORD
