Metadata-Version: 2.1
Name: simple-mailer
Version: 1.1.1
Summary: A simple mailer for web forms
Home-page: https://github.com/zedr/simple-mailer
Author: Rigel Di Scala
Author-email: zedr@zedr.com
License: MIT
Platform: UNKNOWN
Classifier: Programming Language :: Python :: 3
Classifier: License :: OSI Approved :: MIT License
Classifier: Operating System :: OS Independent
Requires-Python: >=3.7
Requires-Dist: bottle (==0.12.18)
Requires-Dist: lxml (==4.6.2)
Requires-Dist: jinja2 (==2.11.2)
